echelle/__init__.py
echelle/echelle.py
echelle/interact.py
echelle/stretching.py
echelle/utils.py
echelle/version.py
echelle-1.5.2.dist-info/licenses/LICENSE.md
echelle-1.5.2.dist-info/METADATA
echelle-1.5.2.dist-info/WHEEL
echelle-1.5.2.dist-info/top_level.txt
echelle-1.5.2.dist-info/RECORD
