Metadata-Version: 2.4
Name: echelle
Version: 1.5.2
Summary: A Python package for plotting and interacting with echelle diagrams.
Author: Daniel Hey
License: MIT
Classifier: Programming Language :: Python :: 3
Requires-Python: >=3.7
License-File: LICENSE.md
Requires-Dist: importlib-metadata; python_version < "3.8"
Provides-Extra: pdf
Requires-Dist: ReportLab>=1.2; extra == "pdf"
Requires-Dist: RXP; extra == "pdf"
Provides-Extra: rest
Requires-Dist: docutils>=0.3; extra == "rest"
Requires-Dist: pack==1.1,==1.3; extra == "rest"
Dynamic: license-file
